tf_utils/__init__.py
tf_utils/main.py
tf_utils/module_versions.py
tf_utils/unused_variables.py
tf_utils/utils.py
py_tf_utils-0.2.1.dist-info/METADATA
py_tf_utils-0.2.1.dist-info/WHEEL
py_tf_utils-0.2.1.dist-info/entry_points.txt
py_tf_utils-0.2.1.dist-info/top_level.txt
py_tf_utils-0.2.1.dist-info/RECORD
