Metadata-Version: 2.1
Name: py-tf-utils
Version: 0.2.1
Summary: Various Terraform Utilities
Home-page: https://github.com/phillipjf/tf-utils
Author: Phillip Ferentinos
Author-email: phillip.jf@gmail.com
License: UNKNOWN
Platform: UNKNOWN
Classifier: Programming Language :: Python :: 3
Requires-Python: >=3.6
Requires-Dist: python-hcl2
